Workbook
Name Assumptions: Assumptions!$E$4:$E$11

Sheet Assumptions
B1: Scenario | C1: Best
A3: Assumption | B3: Best | C3: Base | D3: Worst | E3: Selected
A4: Starting MRR(£) | B4: 50000 | C4: 50000 | D4: 50000 | E4: =CHOOSE(MATCH($C$1,{"Best","Base","Worst"},0),B4,C4,D4) -> 50000
A5: Monthly Revenue Growth% | B5: 0.08 | C5: 0.05 | D5: 0.02 | E5: =CHOOSE(MATCH($C$1,{"Best","Base","Worst"},0),B5,C5,D5) -> 0.08
A6: Churn Rate% | B6: 0.02 | C6: 0.05 | D6: 0.1 | E6: =CHOOSE(MATCH($C$1,{"Best","Base","Worst"},0),B6,C6,D6) -> 0.02
A7: COGS% of Revenue | B7: 0.2 | C7: 0.3 | D7: 0.4 | E7: =CHOOSE(MATCH($C$1,{"Best","Base","Worst"},0),B7,C7,D7) -> 0.2
A8: R&D Expenses (£/month) | B8: 8000 | C8: 12000 | D8: 18000 | E8: =CHOOSE(MATCH($C$1,{"Best","Base","Worst"},0),B8,C8,D8) -> 8000
A9: Sales & Marketing (£/month) | B9: 10000 | C9: 15000 | D9: 22000 | E9: =CHOOSE(MATCH($C$1,{"Best","Base","Worst"},0),B9,C9,D9) -> 10000
A10: G&A Expenses (£/month) | B10: 5000 | C10: 7000 | D10: 10000 | E10: =CHOOSE(MATCH($C$1,{"Best","Base","Worst"},0),B10,C10,D10) -> 5000
A11: Tax Rate % | B11: 0.19 | C11: 0.19 | D11: 0.19 | E11: =CHOOSE(MATCH($C$1,{"Best","Base","Worst"},0),B11,C11,D11) -> 0.19

Sheet P&L
B1: Jan | C1: Feb | D1: Mar | E1: Apr | F1: May | G1: Jun | H1: Jul | I1: Aug | J1: Sep | K1: Oct | L1: Nov | M1: Dec
A2: Revenue | B2: =Assumptions!$E$4 -> 50000 | C2: =B4*(1+Assumptions!$E$5) -> 52920 | D2: =C4*(1+Assumptions!$E$5) -> 56010.528 | E2: =D4*(1+Assumptions!$E$5) -> 59281.543 | F2: =E4*(1+Assumptions!$E$5) -> 62743.585 | G2: =F4*(1+Assumptions!$E$5) -> 66407.81 | H2: =G4*(1+Assumptions!$E$5) -> 70286.026 | I2: =H4*(1+Assumptions!$E$5) -> 74390.73 | J2: =I4*(1+Assumptions!$E$5) -> 78735.149 | ... M2: =L4*(1+Assumptions!$E$5) -> 93350.822
A3: Churn Loss | B3: =-(B2*Assumptions!$E$6) -> -1000 | C3: =-(C2*Assumptions!$E$6) -> -1058.4 | D3: =-(D2*Assumptions!$E$6) -> -1120.2106 | E3: =-(E2*Assumptions!$E$6) -> -1185.6309 | F3: =-(F2*Assumptions!$E$6) -> -1254.8717 | G3: =-(G2*Assumptions!$E$6) -> -1328.1562 | H3: =-(H2*Assumptions!$E$6) -> -1405.7205 | I3: =-(I2*Assumptions!$E$6) -> -1487.8146 | ... M3: =-(M2*Assumptions!$E$6) -> -1867.0164
A4: Net Revenue | B4: =B2+B3 -> 49000 | C4: =C2+C3 -> 51861.6 | D4: =D2+D3 -> 54890.317 | E4: =E2+E3 -> 58095.912 | F4: =F2+F3 -> 61488.713 | G4: =G2+G3 -> 65079.654 | H4: =H2+H3 -> 68880.306 | I4: =I2+I3 -> 72902.916 | ... M4: =M2+M3 -> 91483.806
A5: COGS | B5: =-(B4*(Assumptions!$E$7+0)) -> -9800 | C5: =-(C4*(Assumptions!$E$7+0.001)) -> -10424.182 | D5: =-(D4*(Assumptions!$E$7+0.002)) -> -11087.844 | E5: =-(E4*(Assumptions!$E$7+0.003)) -> -11793.47 | F5: =-(F4*(Assumptions!$E$7+0.004)) -> -12543.698 | G5: =-(G4*(Assumptions!$E$7+0.005)) -> -13341.329 | H5: =-(H4*(Assumptions!$E$7+0.006)) -> -14189.343 | I5: =-(I4*(Assumptions!$E$7+0.007)) -> -15090.904 | J5: =-(J4*(Assumptions!$E$7+0.008)) -> -16049.373 | K5: =-(K4*(Assumptions!$E$7+0.009)) -> -17068.323 | L5: =-(L4*(Assumptions!$E$7+0.01)) -> -18151.549 | M5: =-(M4*(Assumptions!$E$7+0.011)) -> -19303.083
A6: Gross Profit | B6: =B4+B5 -> 39200 | C6: =C4+C5 -> 41437.418 | D6: =D4+D5 -> 43802.473 | E6: =E4+E5 -> 46302.442 | F6: =F4+F5 -> 48945.016 | G6: =G4+G5 -> 51738.325 | H6: =H4+H5 -> 54690.963 | I6: =I4+I5 -> 57812.012 | ... M6: =M4+M5 -> 72180.723
A8: R&D | B8: =-Assumptions!$E$8 -> -8000 | C8: =-Assumptions!$E$8 -> -8000 | D8: =-Assumptions!$E$8 -> -8000 | E8: =-Assumptions!$E$8 -> -8000 | F8: =-Assumptions!$E$8 -> -8000 | G8: =-Assumptions!$E$8 -> -8000 | H8: =-Assumptions!$E$8 -> -8000 | I8: =-Assumptions!$E$8 -> -8000 | ... M8: =-Assumptions!$E$8 -> -8000
A9: Sales & Marketing | B9: =-Assumptions!$E$9 -> -10000 | C9: =-Assumptions!$E$9 -> -10000 | D9: =-Assumptions!$E$9 -> -10000 | E9: =-Assumptions!$E$9 -> -10000 | F9: =-Assumptions!$E$9 -> -10000 | G9: =-Assumptions!$E$9 -> -10000 | H9: =-Assumptions!$E$9 -> -10000 | I9: =-Assumptions!$E$9 -> -10000 | ... M9: =-Assumptions!$E$9 -> -10000
A10: G&A | B10: =-Assumptions!$E$10 -> -5000 | C10: =-Assumptions!$E$10 -> -5000 | D10: =-Assumptions!$E$10 -> -5000 | E10: =-Assumptions!$E$10 -> -5000 | F10: =-Assumptions!$E$10 -> -5000 | G10: =-Assumptions!$E$10 -> -5000 | H10: =-Assumptions!$E$10 -> -5000 | I10: =-Assumptions!$E$10 -> -5000 | ... M10: =-Assumptions!$E$10 -> -5000
A11: Total OpEx | B11: =SUM(B8:B10) -> -23000 | C11: =SUM(C8:C10) -> -23000 | D11: =SUM(D8:D10) -> -23000 | E11: =SUM(E8:E10) -> -23000 | F11: =SUM(F8:F10) -> -23000 | G11: =SUM(G8:G10) -> -23000 | H11: =SUM(H8:H10) -> -23000 | I11: =SUM(I8:I10) -> -23000 | ... M11: =SUM(M8:M10) -> -23000
A13: EBITDA | B13: =B6+B11 -> 16200 | C13: =C6+C11 -> 18437.418 | D13: =D6+D11 -> 20802.473 | E13: =E6+E11 -> 23302.442 | F13: =F6+F11 -> 25945.016 | G13: =G6+G11 -> 28738.325 | H13: =H6+H11 -> 31690.963 | I13: =I6+I11 -> 34812.012 | ... M13: =M6+M11 -> 49180.723
A14: Tax | B14: =IF(B13>0,-(B13*Assumptions!$E$11),0) -> -3078 | C14: =IF(C13>0,-(C13*Assumptions!$E$11),0) -> -3503.1095 | D14: =IF(D13>0,-(D13*Assumptions!$E$11),0) -> -3952.4699 | E14: =IF(E13>0,-(E13*Assumptions!$E$11),0) -> -4427.464 | F14: =IF(F13>0,-(F13*Assumptions!$E$11),0) -> -4929.553 | G14: =IF(G13>0,-(G13*Assumptions!$E$11),0) -> -5460.2818 | H14: =IF(H13>0,-(H13*Assumptions!$E$11),0) -> -6021.2829 | I14: =IF(I13>0,-(I13*Assumptions!$E$11),0) -> -6614.2823 | ... M14: =IF(M13>0,-(M13*Assumptions!$E$11),0) -> -9344.3373
A15: Net Income | B15: =B13+B14 -> 13122 | C15: =C13+C14 -> 14934.309 | D15: =D13+D14 -> 16850.003 | E15: =E13+E14 -> 18874.978 | F15: =F13+F14 -> 21015.463 | G15: =G13+G14 -> 23278.043 | H15: =H13+H14 -> 25669.68 | I15: =I13+I14 -> 28197.73 | ... M15: =M13+M14 -> 39836.385

Sheet CashFlow
B1: Jan | C1: Feb | D1: Mar | E1: Apr | F1: May | G1: Jun | H1: Jul | I1: Aug | J1: Sep | K1: Oct | L1: Nov | M1: Dec
A2: Operating Cash Flow
A3: Net Income | B3: ='P&L'!B15 -> 13122 | C3: ='P&L'!C15 -> 14934.309 | D3: ='P&L'!D15 -> 16850.003 | E3: ='P&L'!E15 -> 18874.978 | F3: ='P&L'!F15 -> 21015.463 | G3: ='P&L'!G15 -> 23278.043 | H3: ='P&L'!H15 -> 25669.68 | I3: ='P&L'!I15 -> 28197.73 | ... M3: ='P&L'!M15 -> 39836.385
A4: Add back: Non-cash items | B4: =500 -> 500 | C4: =500 -> 500 | D4: =500 -> 500 | E4: =500 -> 500 | F4: =500 -> 500 | G4: =500 -> 500 | H4: =500 -> 500 | I4: =500 -> 500 | ... M4: =500 -> 500
A5: Changes in Working Capital | B5: =-200 -> -200 | C5: =-200 -> -200 | D5: =-200 -> -200 | E5: =-200 -> -200 | F5: =-200 -> -200 | G5: =-200 -> -200 | H5: =-200 -> -200 | I5: =-200 -> -200 | ... M5: =-200 -> -200
A6: Total Operating CF | B6: =SUM(B3:B5) -> 13422 | C6: =SUM(C3:C5) -> 15234.309 | D6: =SUM(D3:D5) -> 17150.003 | E6: =SUM(E3:E5) -> 19174.978 | F6: =SUM(F3:F5) -> 21315.463 | G6: =SUM(G3:G5) -> 23578.043 | H6: =SUM(H3:H5) -> 25969.68 | I6: =SUM(I3:I5) -> 28497.73 | ... M6: =SUM(M3:M5) -> 40136.385
A8: Investing Activities
A9: Capex/Software Investment | B9: =-2000 -> -2000 | C9: =-2000 -> -2000 | D9: =-2000 -> -2000 | E9: =-2000 -> -2000 | F9: =-2000 -> -2000 | G9: =-2000 -> -2000 | H9: =-2000 -> -2000 | I9: =-2000 -> -2000 | ... M9: =-2000 -> -2000
A10: Total Investing CF | B10: =B9 -> -2000 | C10: =C9 -> -2000 | D10: =D9 -> -2000 | E10: =E9 -> -2000 | F10: =F9 -> -2000 | G10: =G9 -> -2000 | H10: =H9 -> -2000 | I10: =I9 -> -2000 | ... M10: =M9 -> -2000
A12: Financing Activities
A13: Equity/Funding Raised | B13: =100000 -> 100000 | C13: =0 -> 0 | D13: =0 -> 0 | E13: =0 -> 0 | F13: =0 -> 0 | G13: =0 -> 0 | H13: =0 -> 0 | I13: =0 -> 0 | J13: =0 -> 0 | ... M13: =0 -> 0
A14: Total Financing CF | B14: =B13 -> 100000 | C14: =C13 -> 0 | D14: =D13 -> 0 | E14: =E13 -> 0 | F14: =F13 -> 0 | G14: =G13 -> 0 | H14: =H13 -> 0 | I14: =I13 -> 0 | ... M14: =M13 -> 0
A16: Net Cash Movement | B16: =B6+B10+B14 -> 111422 | C16: =C6+C10+C14 -> 13234.309 | D16: =D6+D10+D14 -> 15150.003 | E16: =E6+E10+E14 -> 17174.978 | F16: =F6+F10+F14 -> 19315.463 | G16: =G6+G10+G14 -> 21578.043 | H16: =H6+H10+H14 -> 23969.68 | I16: =I6+I10+I14 -> 26497.73 | ... M16: =M6+M10+M14 -> 38136.385
A17: Opening Cash Balance | B17: =0 -> 0 | C17: =B18 -> 111422 | D17: =C18 -> 124656.31 | E17: =D18 -> 139806.31 | F17: =E18 -> 156981.29 | G17: =F18 -> 176296.75 | H17: =G18 -> 197874.8 | I17: =H18 -> 221844.48 | J17: =I18 -> 248342.21 | ... M17: =L18 -> 344487.16
A18: Closing Cash Balance | B18: =B17+B16 -> 111422 | C18: =C17+C16 -> 124656.31 | D18: =D17+D16 -> 139806.31 | E18: =E17+E16 -> 156981.29 | F18: =F17+F16 -> 176296.75 | G18: =G17+G16 -> 197874.8 | H18: =H17+H16 -> 221844.48 | I18: =I17+I16 -> 248342.21 | ... M18: =M17+M16 -> 382623.54

Sheet Dashboard
B2: Total Annual Revenue | D2: Gross Profit Margin | F2: Net Income | H2: Closing Cash (Dec)
B3: =SUM('P&L'!B4:M4) -> 818946.23 | D3: =SUM('P&L'!B6:M6)/SUM('P&L'!B4:M4) -> 0.79382884 | F3: =SUM('P&L'!B15:M15) -> 303023.54 | H3: =CashFlow!M18 -> 382623.54
A6: Month | B6: Net Revenue | C6: Net Income | E6: Month | F6: Gross Margin % | H6: ="Model Scenario: "&Assumptions!C1 -> Model Scenario: Best
A7: Jan | B7: ='P&L'!B4 -> 49000 | C7: ='P&L'!B15 -> 13122 | E7: Jan | F7: ='P&L'!B6/'P&L'!B4 -> 0.8
A8: Feb | B8: ='P&L'!C4 -> 51861.6 | C8: ='P&L'!C15 -> 14934.309 | E8: Feb | F8: ='P&L'!C6/'P&L'!C4 -> 0.799
A9: Mar | B9: ='P&L'!D4 -> 54890.317 | C9: ='P&L'!D15 -> 16850.003 | E9: Mar | F9: ='P&L'!D6/'P&L'!D4 -> 0.798
A10: Apr | B10: ='P&L'!E4 -> 58095.912 | C10: ='P&L'!E15 -> 18874.978 | E10: Apr | F10: ='P&L'!E6/'P&L'!E4 -> 0.797
A11: May | B11: ='P&L'!F4 -> 61488.713 | C11: ='P&L'!F15 -> 21015.463 | E11: May | F11: ='P&L'!F6/'P&L'!F4 -> 0.796
A12: Jun | B12: ='P&L'!G4 -> 65079.654 | C12: ='P&L'!G15 -> 23278.043 | E12: Jun | F12: ='P&L'!G6/'P&L'!G4 -> 0.795
A13: Jul | B13: ='P&L'!H4 -> 68880.306 | C13: ='P&L'!H15 -> 25669.68 | E13: Jul | F13: ='P&L'!H6/'P&L'!H4 -> 0.794
A14: Aug | B14: ='P&L'!I4 -> 72902.916 | C14: ='P&L'!I15 -> 28197.73 | E14: Aug | F14: ='P&L'!I6/'P&L'!I4 -> 0.793
A15: Sep | B15: ='P&L'!J4 -> 77160.446 | C15: ='P&L'!J15 -> 30869.969 | E15: Sep | F15: ='P&L'!J6/'P&L'!J4 -> 0.792
A16: Oct | B16: ='P&L'!K4 -> 81666.616 | C16: ='P&L'!K15 -> 33694.618 | E16: Oct | F16: ='P&L'!K6/'P&L'!K4 -> 0.791
A17: Nov | B17: ='P&L'!L4 -> 86435.946 | C17: ='P&L'!L15 -> 36680.362 | E17: Nov | F17: ='P&L'!L6/'P&L'!L4 -> 0.79
A18: Dec | B18: ='P&L'!M4 -> 91483.806 | C18: ='P&L'!M15 -> 39836.385 | E18: Dec | F18: ='P&L'!M6/'P&L'!M4 -> 0.789

Sheet Variance
B1: Budget | C1: Actuals | D1: Variance(£) | E1: Variance(%) | F1: Favourable?
A2: Revenue | B2: =SUM('P&L'!B4:M4) -> 818946.23 | C2: =B2*0.93 -> 761620 | D2: =C2-B2 -> -57326.236 | E2: =D2/B2 -> -0.07 | F2: =IF(A2="Revenue",D2,-D2) -> -57326.236
A3: COGS | B3: =SUM('P&L'!B5:M5) -> -168843.1 | C3: =B3*1.08 -> -182350.54 | D3: =C3-B3 -> -13507.448 | E3: =D3/B3 -> 0.08 | F3: =IF(A3="Revenue",D3,-D3) -> 13507.448
A4: Gross Profit | B4: =SUM('P&L'!B6:M6) -> 650103.14 | C4: =C2+C3 -> 579269.45 | D4: =C4-B4 -> -70833.684 | E4: =D4/B4 -> -0.10895761 | F4: =IF(A4="Revenue",D4,-D4) -> 70833.684
A5: Total OpEx | B5: =SUM('P&L'!B11:M11) -> -276000 | C5: =B5*1.05 -> -289800 | D5: =C5-B5 -> -13800 | E5: =D5/B5 -> 0.05 | F5: =IF(A5="Revenue",D5,-D5) -> 13800
A6: EBITDA | B6: =SUM('P&L'!B13:M13) -> 374103.14 | C6: =C4+C5 -> 289469.45 | D6: =C6-B6 -> -84633.684 | E6: =D6/B6 -> -0.22623089 | F6: =IF(A6="Revenue",D6,-D6) -> 84633.684
A7: Net Income | B7: =SUM('P&L'!B15:M15) -> 303023.54 | C7: =C6-(C6*Assumptions!$E$11) -> 234470.26 | D7: =C7-B7 -> -68553.284 | E7: =D7/B7 -> -0.22623089 | F7: =IF(A7="Revenue",D7,-D7) -> 68553.284
A10: Sensitivity: Net Income by Growth Rate vs COGS %
B11: 20% COGS | C11: 30% COGS | D11: 40% COGS | E11: 50% COGS
A12: 2% Growth | B12: {=SUMPRODUCT((50000*((1+0.02-Assumptions!$E$6)^(ROW(INDIRECT("1:12"))-1)))*(1-0.2))-((Assumptions!$E$8+Assumptions!$E$9+Assumptions!$E$10)*12)} -> 204000 | C12: {=SUMPRODUCT((50000*((1+0.02-Assumptions!$E$6)^(ROW(INDIRECT("1:12"))-1)))*(1-0.3))-((Assumptions!$E$8+Assumptions!$E$9+Assumptions!$E$10)*12)} -> 144000 | D12: {=SUMPRODUCT((50000*((1+0.02-Assumptions!$E$6)^(ROW(INDIRECT("1:12"))-1)))*(1-0.4))-((Assumptions!$E$8+Assumptions!$E$9+Assumptions!$E$10)*12)} -> 84000 | E12: {=SUMPRODUCT((50000*((1+0.02-Assumptions!$E$6)^(ROW(INDIRECT("1:12"))-1)))*(1-0.5))-((Assumptions!$E$8+Assumptions!$E$9+Assumptions!$E$10)*12)} -> 24000
A13: 5% Growth | B13: {=SUMPRODUCT((50000*((1+0.05-Assumptions!$E$6)^(ROW(INDIRECT("1:12"))-1)))*(1-0.2))-((Assumptions!$E$8+Assumptions!$E$9+Assumptions!$E$10)*12)} -> 291681.18 | C13: {=SUMPRODUCT((50000*((1+0.05-Assumptions!$E$6)^(ROW(INDIRECT("1:12"))-1)))*(1-0.3))-((Assumptions!$E$8+Assumptions!$E$9+Assumptions!$E$10)*12)} -> 220721.03 | D13: {=SUMPRODUCT((50000*((1+0.05-Assumptions!$E$6)^(ROW(INDIRECT("1:12"))-1)))*(1-0.4))-((Assumptions!$E$8+Assumptions!$E$9+Assumptions!$E$10)*12)} -> 149760.89 | E13: {=SUMPRODUCT((50000*((1+0.05-Assumptions!$E$6)^(ROW(INDIRECT("1:12"))-1)))*(1-0.5))-((Assumptions!$E$8+Assumptions!$E$9+Assumptions!$E$10)*12)} -> 78800.739
A14: 8% Growth | B14: {=SUMPRODUCT((50000*((1+0.08-Assumptions!$E$6)^(ROW(INDIRECT("1:12"))-1)))*(1-0.2))-((Assumptions!$E$8+Assumptions!$E$9+Assumptions!$E$10)*12)} -> 398797.65 | C14: {=SUMPRODUCT((50000*((1+0.08-Assumptions!$E$6)^(ROW(INDIRECT("1:12"))-1)))*(1-0.3))-((Assumptions!$E$8+Assumptions!$E$9+Assumptions!$E$10)*12)} -> 314447.94 | D14: {=SUMPRODUCT((50000*((1+0.08-Assumptions!$E$6)^(ROW(INDIRECT("1:12"))-1)))*(1-0.4))-((Assumptions!$E$8+Assumptions!$E$9+Assumptions!$E$10)*12)} -> 230098.24 | E14: {=SUMPRODUCT((50000*((1+0.08-Assumptions!$E$6)^(ROW(INDIRECT("1:12"))-1)))*(1-0.5))-((Assumptions!$E$8+Assumptions!$E$9+Assumptions!$E$10)*12)} -> 145748.53
A15: 10% Growth | B15: {=SUMPRODUCT((50000*((1+0.1-Assumptions!$E$6)^(ROW(INDIRECT("1:12"))-1)))*(1-0.2))-((Assumptions!$E$8+Assumptions!$E$9+Assumptions!$E$10)*12)} -> 483085.06 | C15: {=SUMPRODUCT((50000*((1+0.1-Assumptions!$E$6)^(ROW(INDIRECT("1:12"))-1)))*(1-0.3))-((Assumptions!$E$8+Assumptions!$E$9+Assumptions!$E$10)*12)} -> 388199.43 | D15: {=SUMPRODUCT((50000*((1+0.1-Assumptions!$E$6)^(ROW(INDIRECT("1:12"))-1)))*(1-0.4))-((Assumptions!$E$8+Assumptions!$E$9+Assumptions!$E$10)*12)} -> 293313.79 | E15: {=SUMPRODUCT((50000*((1+0.1-Assumptions!$E$6)^(ROW(INDIRECT("1:12"))-1)))*(1-0.5))-((Assumptions!$E$8+Assumptions!$E$9+Assumptions!$E$10)*12)} -> 198428.16
